Classfile /C:/Users/KUCOLE/workspace/junit.sample/jacoco-gosu-filter/src/test/resources/bytecode/PolicyPeriodEnhancement.class
  Last modified 12 nov. 2025; size 2948 bytes
  SHA-256 checksum f8f49af830def1f8ebc3d0d76cff55e3b149af49a17e17758a42628ca887d223
  Compiled from "PolicyPeriodEnhancement.gsx"
public class enhancement.PolicyPeriodEnhancement
  minor version: 0
  major version: 52
  flags: (0x0021) ACC_PUBLIC, ACC_SUPER
  this_class: #2                          // enhancement/PolicyPeriodEnhancement
  super_class: #4                         // java/lang/Object
  interfaces: 0, fields: 1, methods: 5, attributes: 2
Constant pool:
    #1 = Utf8               enhancement/PolicyPeriodEnhancement
    #2 = Class              #1            // enhancement/PolicyPeriodEnhancement
    #3 = Utf8               java/lang/Object
    #4 = Class              #3            // java/lang/Object
    #5 = Utf8               PolicyPeriodEnhancement.gsx
    #6 = Utf8               ENHANCED$TYPE
    #7 = Utf8               Lentity/PolicyPeriod;
    #8 = Utf8               <clinit>
    #9 = Utf8               ()V
   #10 = Utf8               manifold/internal/runtime/Bootstrap
   #11 = Class              #10           // manifold/internal/runtime/Bootstrap
   #12 = Utf8               init
   #13 = Utf8               ()Z
   #14 = NameAndType        #12:#13       // init:()Z
   #15 = Methodref          #11.#14       // manifold/internal/runtime/Bootstrap.init:()Z
   #16 = Utf8               getFirstPeriodInTermCreateTime_Ext
   #17 = Utf8               (Lentity/PolicyPeriod;)Ljava/util/Date;
   #18 = Utf8               entity/PolicyPeriod
   #19 = Class              #18           // entity/PolicyPeriod
   #20 = Utf8               getFirstPeriodInTerm
   #21 = Utf8               ()Lentity/PolicyPeriod;
   #22 = NameAndType        #20:#21       // getFirstPeriodInTerm:()Lentity/PolicyPeriod;
   #23 = Methodref          #19.#22       // entity/PolicyPeriod.getFirstPeriodInTerm:()Lentity/PolicyPeriod;
   #24 = Utf8               java/util/Date
   #25 = Class              #24           // java/util/Date
   #26 = Utf8               getCreateTime
   #27 = Utf8               ()Ljava/util/Date;
   #28 = NameAndType        #26:#27       // getCreateTime:()Ljava/util/Date;
   #29 = Methodref          #19.#28       // entity/PolicyPeriod.getCreateTime:()Ljava/util/Date;
   #30 = Utf8               $that$
   #31 = Utf8               getAvailableBrandConceptsForProdCode
   #32 = Utf8               (Lentity/PolicyPeriod;)Ljava/util/List;
   #33 = Utf8               (Lentity/PolicyPeriod;)Ljava/util/List<Lentity/BrandConcept_Ext;>;
   #34 = Utf8               getProducerCodeOfRecord
   #35 = Utf8               ()Lentity/ProducerCode;
   #36 = NameAndType        #34:#35       // getProducerCodeOfRecord:()Lentity/ProducerCode;
   #37 = Methodref          #19.#36       // entity/PolicyPeriod.getProducerCodeOfRecord:()Lentity/ProducerCode;
   #38 = Utf8               [Lentity/ProdCodeBrandConcept_Ext;
   #39 = Class              #38           // "[Lentity/ProdCodeBrandConcept_Ext;"
   #40 = Utf8               entity/ProducerCode
   #41 = Class              #40           // entity/ProducerCode
   #42 = Utf8               getBrandConcepts_Ext
   #43 = Utf8               ()[Lentity/ProdCodeBrandConcept_Ext;
   #44 = NameAndType        #42:#43       // getBrandConcepts_Ext:()[Lentity/ProdCodeBrandConcept_Ext;
   #45 = Methodref          #41.#44       // entity/ProducerCode.getBrandConcepts_Ext:()[Lentity/ProdCodeBrandConcept_Ext;
   #46 = Utf8               java/lang/Boolean
   #47 = Class              #46           // java/lang/Boolean
   #48 = Utf8               java/lang/NullPointerException
   #49 = Class              #48           // java/lang/NullPointerException
   #50 = Utf8               <init>
   #51 = NameAndType        #50:#9        // "<init>":()V
   #52 = Methodref          #49.#51       // java/lang/NullPointerException."<init>":()V
   #53 = Utf8               gw/lang/enhancements/CoreArrayEnhancement
   #54 = Class              #53           // gw/lang/enhancements/CoreArrayEnhancement
   #55 = Utf8               isHasElements
   #56 = Utf8               ([Ljava/lang/Object;)Ljava/lang/Boolean;
   #57 = NameAndType        #55:#56       // isHasElements:([Ljava/lang/Object;)Ljava/lang/Boolean;
   #58 = Methodref          #54.#57       // gw/lang/enhancements/CoreArrayEnhancement.isHasElements:([Ljava/lang/Object;)Ljava/lang/Boolean;
   #59 = Utf8               booleanValue
   #60 = NameAndType        #59:#13       // booleanValue:()Z
   #61 = Methodref          #47.#60       // java/lang/Boolean.booleanValue:()Z
   #62 = Utf8               entity/BrandConcept_Ext
   #63 = Class              #62           // entity/BrandConcept_Ext
   #64 = Utf8               [Lentity/BrandConcept_Ext;
   #65 = Class              #64           // "[Lentity/BrandConcept_Ext;"
   #66 = Utf8               entity/ProdCodeBrandConcept_Ext
   #67 = Class              #66           // entity/ProdCodeBrandConcept_Ext
   #68 = Utf8               getBrandConcept
   #69 = Utf8               ()Lentity/BrandConcept_Ext;
   #70 = NameAndType        #68:#69       // getBrandConcept:()Lentity/BrandConcept_Ext;
   #71 = Methodref          #67.#70       // entity/ProdCodeBrandConcept_Ext.getBrandConcept:()Lentity/BrandConcept_Ext;
   #72 = Utf8               toList
   #73 = Utf8               ([Ljava/lang/Object;)Ljava/util/List;
   #74 = NameAndType        #72:#73       // toList:([Ljava/lang/Object;)Ljava/util/List;
   #75 = Methodref          #54.#74       // gw/lang/enhancements/CoreArrayEnhancement.toList:([Ljava/lang/Object;)Ljava/util/List;
   #76 = Utf8               brandConcepts
   #77 = Utf8               java/util/List
   #78 = Class              #77           // java/util/List
   #79 = Utf8               getFirstPeriodProducerCodeName
   #80 = Utf8               (Lentity/PolicyPeriod;)Ljava/lang/String;
   #81 = Utf8               gw/lang/reflect/SimpleTypeLazyTypeResolver
   #82 = Class              #81           // gw/lang/reflect/SimpleTypeLazyTypeResolver
   #83 = Utf8               entity.ProdCodeBrandConcept_Ext
   #84 = String             #83           // entity.ProdCodeBrandConcept_Ext
   #85 = Utf8               _default_
   #86 = String             #85           // _default_
   #87 = Utf8               (Ljava/lang/String;Ljava/lang/String;)V
   #88 = NameAndType        #50:#87       // "<init>":(Ljava/lang/String;Ljava/lang/String;)V
   #89 = Methodref          #82.#88       // gw/lang/reflect/SimpleTypeLazyTypeResolver."<init>":(Ljava/lang/String;Ljava/lang/String;)V
   #90 = Utf8               first
   #91 = Utf8               ([Ljava/lang/Object;Lgw/lang/reflect/LazyTypeResolver;)Ljava/lang/Object;
   #92 = NameAndType        #90:#91       // first:([Ljava/lang/Object;Lgw/lang/reflect/LazyTypeResolver;)Ljava/lang/Object;
   #93 = Methodref          #54.#92       // gw/lang/enhancements/CoreArrayEnhancement.first:([Ljava/lang/Object;Lgw/lang/reflect/LazyTypeResolver;)Ljava/lang/Object;
   #94 = Utf8               java/lang/String
   #95 = Class              #94           // java/lang/String
   #96 = Utf8               getName
   #97 = Utf8               ()Ljava/lang/String;
   #98 = NameAndType        #96:#97       // getName:()Ljava/lang/String;
   #99 = Methodref          #63.#98       // entity/BrandConcept_Ext.getName:()Ljava/lang/String;
  #100 = Utf8               isProducerCodeExists
  #101 = Utf8               (Lentity/PolicyPeriod;)Z
  #102 = Utf8               Code
  #103 = Utf8               StackMapTable
  #104 = Utf8               LineNumberTable
  #105 = Utf8               LocalVariableTable
  #106 = Utf8               Signature
  #107 = Utf8               SourceFile
  #108 = Utf8               GosuVersion
{
  private static final entity.PolicyPeriod ENHANCED$TYPE;
    descriptor: Lentity/PolicyPeriod;
    flags: (0x101a) ACC_PRIVATE, ACC_STATIC, ACC_FINAL, ACC_SYNTHETIC

  static {};
    descriptor: ()V
    flags: (0x0008) ACC_STATIC
    Code:
      stack=1, locals=0, args_size=0
         0: invokestatic  #15                 // Method manifold/internal/runtime/Bootstrap.init:()Z
         3: pop
         4: return

  public static java.util.Date getFirstPeriodInTermCreateTime_Ext(entity.PolicyPeriod);
    descriptor: (Lentity/PolicyPeriod;)Ljava/util/Date;
    flags: (0x0009) ACC_PUBLIC, ACC_STATIC
    Code:
      stack=1, locals=2, args_size=1
         0: aload_0
         1: invokevirtual #23                 // Method entity/PolicyPeriod.getFirstPeriodInTerm:()Lentity/PolicyPeriod;
         4: astore_1
         5: aload_1
         6: ifnonnull     16
         9: aconst_null
        10: checkcast     #25                 // class java/util/Date
        13: goto          20
        16: aload_1
        17: invokevirtual #29                 // Method entity/PolicyPeriod.getCreateTime:()Ljava/util/Date;
        20: areturn
      StackMapTable: number_of_entries = 2
        frame_type = 252 /* append */
          offset_delta = 16
          locals = [ class entity/PolicyPeriod ]
        frame_type = 67 /* same_locals_1_stack_item */
          stack = [ class java/util/Date ]
      LineNumberTable:
        line 13: 0
      LocalVariableTable:
        Start  Length  Slot  Name   Signature
            0      21     0 $that$   Lentity/PolicyPeriod;

  public static java.util.List<entity.BrandConcept_Ext> getAvailableBrandConceptsForProdCode(entity.PolicyPeriod);
    descriptor: (Lentity/PolicyPeriod;)Ljava/util/List;
    flags: (0x0009) ACC_PUBLIC, ACC_STATIC
    Code:
      stack=3, locals=10, args_size=1
         0: aload_0
         1: invokevirtual #37                 // Method entity/PolicyPeriod.getProducerCodeOfRecord:()Lentity/ProducerCode;
         4: astore_1
         5: aload_1
         6: ifnonnull     16
         9: aconst_null
        10: checkcast     #39                 // class "[Lentity/ProdCodeBrandConcept_Ext;"
        13: goto          20
        16: aload_1
        17: invokevirtual #45                 // Method entity/ProducerCode.getBrandConcepts_Ext:()[Lentity/ProdCodeBrandConcept_Ext;
        20: astore_1
        21: aload_1
        22: astore_2
        23: aload_2
        24: ifnonnull     34
        27: aconst_null
        28: checkcast     #47                 // class java/lang/Boolean
        31: goto          52
        34: aload_2
        35: astore_3
        36: aload_3
        37: ifnonnull     48
        40: new           #49                 // class java/lang/NullPointerException
        43: dup
        44: invokespecial #52                 // Method java/lang/NullPointerException."<init>":()V
        47: athrow
        48: aload_3
        49: invokestatic  #58                 // Method gw/lang/enhancements/CoreArrayEnhancement.isHasElements:([Ljava/lang/Object;)Ljava/lang/Boolean;
        52: astore_2
        53: aload_2
        54: ifnonnull     61
        57: iconst_0
        58: goto          65
        61: aload_2
        62: invokevirtual #61                 // Method java/lang/Boolean.booleanValue:()Z
        65: ifeq          201
        68: aload_1
        69: astore_2
        70: aload_2
        71: ifnonnull     84
        74: iconst_0
        75: anewarray     #63                 // class entity/BrandConcept_Ext
        78: checkcast     #65                 // class "[Lentity/BrandConcept_Ext;"
        81: goto          181
        84: aload_2
        85: arraylength
        86: anewarray     #63                 // class entity/BrandConcept_Ext
        89: astore_3
        90: aload_2
        91: astore        4
        93: iconst_m1
        94: aload         4
        96: ifnonnull     103
        99: iconst_m1
       100: goto          106
       103: aload         4
       105: arraylength
       106: iadd
       107: istore        5
       109: iconst_m1
       110: istore        6
       112: aconst_null
       113: astore        7
       115: iconst_m1
       116: istore        8
       118: aload         4
       120: ifnull        177
       123: iload         6
       125: iload         5
       127: if_icmpeq     177
       130: iload         6
       132: iconst_1
       133: iadd
       134: istore        6
       136: aload         4
       138: iload         6
       140: aaload
       141: astore        7
       143: iload         8
       145: iconst_1
       146: iadd
       147: istore        8
       149: aload_3
       150: iload         8
       152: aload         7
       154: astore        9
       156: aload         9
       158: ifnonnull     168
       161: aconst_null
       162: checkcast     #63                 // class entity/BrandConcept_Ext
       165: goto          173
       168: aload         9
       170: invokevirtual #71                 // Method entity/ProdCodeBrandConcept_Ext.getBrandConcept:()Lentity/BrandConcept_Ext;
       173: aastore
       174: goto          123
       177: aload_3
       178: checkcast     #65                 // class "[Lentity/BrandConcept_Ext;"
       181: astore_2
       182: aload_2
       183: ifnonnull     194
       186: new           #49                 // class java/lang/NullPointerException
       189: dup
       190: invokespecial #52                 // Method java/lang/NullPointerException."<init>":()V
       193: athrow
       194: aload_2
       195: invokestatic  #75                 // Method gw/lang/enhancements/CoreArrayEnhancement.toList:([Ljava/lang/Object;)Ljava/util/List;
       198: goto          202
       201: aconst_null
       202: areturn
      StackMapTable: number_of_entries = 18
        frame_type = 252 /* append */
          offset_delta = 16
          locals = [ class entity/ProducerCode ]
        frame_type = 67 /* same_locals_1_stack_item */
          stack = [ class "[Lentity/ProdCodeBrandConcept_Ext;" ]
        frame_type = 255 /* full_frame */
          offset_delta = 13
          locals = [ class entity/PolicyPeriod, class "[Lentity/ProdCodeBrandConcept_Ext;", class "[Lentity/ProdCodeBrandConcept_Ext;" ]
          stack = []
        frame_type = 252 /* append */
          offset_delta = 13
          locals = [ class "[Lentity/ProdCodeBrandConcept_Ext;" ]
        frame_type = 255 /* full_frame */
          offset_delta = 3
          locals = [ class entity/PolicyPeriod, class "[Lentity/ProdCodeBrandConcept_Ext;", class "[Lentity/ProdCodeBrandConcept_Ext;" ]
          stack = [ class java/lang/Boolean ]
        frame_type = 255 /* full_frame */
          offset_delta = 8
          locals = [ class entity/PolicyPeriod, class "[Lentity/ProdCodeBrandConcept_Ext;", class java/lang/Boolean ]
          stack = []
        frame_type = 67 /* same_locals_1_stack_item */
          stack = [ int ]
        frame_type = 255 /* full_frame */
          offset_delta = 18
          locals = [ class entity/PolicyPeriod, class "[Lentity/ProdCodeBrandConcept_Ext;", class "[Lentity/ProdCodeBrandConcept_Ext;" ]
          stack = []
        frame_type = 255 /* full_frame */
          offset_delta = 18
          locals = [ class entity/PolicyPeriod, class "[Lentity/ProdCodeBrandConcept_Ext;", class "[Lentity/ProdCodeBrandConcept_Ext;", class "[Lentity/BrandConcept_Ext;", class "[Lentity/ProdCodeBrandConcept_Ext;" ]
          stack = [ int ]
        frame_type = 255 /* full_frame */
          offset_delta = 2
          locals = [ class entity/PolicyPeriod, class "[Lentity/ProdCodeBrandConcept_Ext;", class "[Lentity/ProdCodeBrandConcept_Ext;", class "[Lentity/BrandConcept_Ext;", class "[Lentity/ProdCodeBrandConcept_Ext;" ]
          stack = [ int, int ]
        frame_type = 255 /* full_frame */
          offset_delta = 16
          locals = [ class entity/PolicyPeriod, class "[Lentity/ProdCodeBrandConcept_Ext;", class "[Lentity/ProdCodeBrandConcept_Ext;", class "[Lentity/BrandConcept_Ext;", class "[Lentity/ProdCodeBrandConcept_Ext;", int, int, class entity/ProdCodeBrandConcept_Ext, int ]
          stack = []
        frame_type = 255 /* full_frame */
          offset_delta = 44
          locals = [ class entity/PolicyPeriod, class "[Lentity/ProdCodeBrandConcept_Ext;", class "[Lentity/ProdCodeBrandConcept_Ext;", class "[Lentity/BrandConcept_Ext;", class "[Lentity/ProdCodeBrandConcept_Ext;", int, int, class entity/ProdCodeBrandConcept_Ext, int, class entity/ProdCodeBrandConcept_Ext ]
          stack = [ class "[Lentity/BrandConcept_Ext;", int ]
        frame_type = 255 /* full_frame */
          offset_delta = 4
          locals = [ class entity/PolicyPeriod, class "[Lentity/ProdCodeBrandConcept_Ext;", class "[Lentity/ProdCodeBrandConcept_Ext;", class "[Lentity/BrandConcept_Ext;", class "[Lentity/ProdCodeBrandConcept_Ext;", int, int, class entity/ProdCodeBrandConcept_Ext, int, class entity/ProdCodeBrandConcept_Ext ]
          stack = [ class "[Lentity/BrandConcept_Ext;", int, class entity/BrandConcept_Ext ]
        frame_type = 250 /* chop */
          offset_delta = 3
        frame_type = 255 /* full_frame */
          offset_delta = 3
          locals = [ class entity/PolicyPeriod, class "[Lentity/ProdCodeBrandConcept_Ext;", class "[Lentity/ProdCodeBrandConcept_Ext;" ]
          stack = [ class "[Lentity/BrandConcept_Ext;" ]
        frame_type = 255 /* full_frame */
          offset_delta = 12
          locals = [ class entity/PolicyPeriod, class "[Lentity/ProdCodeBrandConcept_Ext;", class "[Lentity/BrandConcept_Ext;" ]
          stack = []
        frame_type = 255 /* full_frame */
          offset_delta = 6
          locals = [ class entity/PolicyPeriod, class "[Lentity/ProdCodeBrandConcept_Ext;", class java/lang/Boolean ]
          stack = []
        frame_type = 255 /* full_frame */
          offset_delta = 0
          locals = [ class entity/PolicyPeriod, class "[Lentity/ProdCodeBrandConcept_Ext;", class java/lang/Object ]
          stack = [ class java/util/List ]
      LineNumberTable:
        line 21: 0
        line 22: 21
      LocalVariableTable:
        Start  Length  Slot  Name   Signature
            0     203     0 $that$   Lentity/PolicyPeriod;
           21     182     1 brandConcepts   [Lentity/ProdCodeBrandConcept_Ext;
    Signature: #33                          // (Lentity/PolicyPeriod;)Ljava/util/List<Lentity/BrandConcept_Ext;>;

  public static java.lang.String getFirstPeriodProducerCodeName(entity.PolicyPeriod);
    descriptor: (Lentity/PolicyPeriod;)Ljava/lang/String;
    flags: (0x0009) ACC_PUBLIC, ACC_STATIC
    Code:
      stack=4, locals=4, args_size=1
         0: aload_0
         1: invokevirtual #23                 // Method entity/PolicyPeriod.getFirstPeriodInTerm:()Lentity/PolicyPeriod;
         4: astore_1
         5: aload_1
         6: ifnonnull     16
         9: aconst_null
        10: checkcast     #41                 // class entity/ProducerCode
        13: goto          20
        16: aload_1
        17: invokevirtual #37                 // Method entity/PolicyPeriod.getProducerCodeOfRecord:()Lentity/ProducerCode;
        20: astore_1
        21: aload_1
        22: ifnonnull     32
        25: aconst_null
        26: checkcast     #39                 // class "[Lentity/ProdCodeBrandConcept_Ext;"
        29: goto          36
        32: aload_1
        33: invokevirtual #45                 // Method entity/ProducerCode.getBrandConcepts_Ext:()[Lentity/ProdCodeBrandConcept_Ext;
        36: astore_1
        37: aload_1
        38: ifnonnull     48
        41: aconst_null
        42: checkcast     #4                  // class java/lang/Object
        45: goto          79
        48: aload_1
        49: astore_2
        50: new           #82                 // class gw/lang/reflect/SimpleTypeLazyTypeResolver
        53: dup
        54: ldc           #84                 // String entity.ProdCodeBrandConcept_Ext
        56: ldc           #86                 // String _default_
        58: invokespecial #89                 // Method gw/lang/reflect/SimpleTypeLazyTypeResolver."<init>":(Ljava/lang/String;Ljava/lang/String;)V
        61: astore_3
        62: aload_2
        63: ifnonnull     74
        66: new           #49                 // class java/lang/NullPointerException
        69: dup
        70: invokespecial #52                 // Method java/lang/NullPointerException."<init>":()V
        73: athrow
        74: aload_2
        75: aload_3
        76: invokestatic  #93                 // Method gw/lang/enhancements/CoreArrayEnhancement.first:([Ljava/lang/Object;Lgw/lang/reflect/LazyTypeResolver;)Ljava/lang/Object;
        79: checkcast     #67                 // class entity/ProdCodeBrandConcept_Ext
        82: astore_1
        83: aload_1
        84: ifnonnull     94
        87: aconst_null
        88: checkcast     #63                 // class entity/BrandConcept_Ext
        91: goto          98
        94: aload_1
        95: invokevirtual #71                 // Method entity/ProdCodeBrandConcept_Ext.getBrandConcept:()Lentity/BrandConcept_Ext;
        98: astore_1
        99: aload_1
       100: ifnonnull     110
       103: aconst_null
       104: checkcast     #95                 // class java/lang/String
       107: goto          114
       110: aload_1
       111: invokevirtual #99                 // Method entity/BrandConcept_Ext.getName:()Ljava/lang/String;
       114: areturn
      StackMapTable: number_of_entries = 11
        frame_type = 252 /* append */
          offset_delta = 16
          locals = [ class entity/PolicyPeriod ]
        frame_type = 67 /* same_locals_1_stack_item */
          stack = [ class entity/ProducerCode ]
        frame_type = 255 /* full_frame */
          offset_delta = 11
          locals = [ class entity/PolicyPeriod, class entity/ProducerCode ]
          stack = []
        frame_type = 67 /* same_locals_1_stack_item */
          stack = [ class "[Lentity/ProdCodeBrandConcept_Ext;" ]
        frame_type = 255 /* full_frame */
          offset_delta = 11
          locals = [ class entity/PolicyPeriod, class "[Lentity/ProdCodeBrandConcept_Ext;" ]
          stack = []
        frame_type = 253 /* append */
          offset_delta = 25
          locals = [ class "[Lentity/ProdCodeBrandConcept_Ext;", class gw/lang/reflect/SimpleTypeLazyTypeResolver ]
        frame_type = 255 /* full_frame */
          offset_delta = 4
          locals = [ class entity/PolicyPeriod, class "[Lentity/ProdCodeBrandConcept_Ext;" ]
          stack = [ class java/lang/Object ]
        frame_type = 255 /* full_frame */
          offset_delta = 14
          locals = [ class entity/PolicyPeriod, class entity/ProdCodeBrandConcept_Ext ]
          stack = []
        frame_type = 67 /* same_locals_1_stack_item */
          stack = [ class entity/BrandConcept_Ext ]
        frame_type = 255 /* full_frame */
          offset_delta = 11
          locals = [ class entity/PolicyPeriod, class entity/BrandConcept_Ext ]
          stack = []
        frame_type = 67 /* same_locals_1_stack_item */
          stack = [ class java/lang/String ]
      LineNumberTable:
        line 30: 0
      LocalVariableTable:
        Start  Length  Slot  Name   Signature
            0     115     0 $that$   Lentity/PolicyPeriod;

  public static boolean isProducerCodeExists(entity.PolicyPeriod);
    descriptor: (Lentity/PolicyPeriod;)Z
    flags: (0x0009) ACC_PUBLIC, ACC_STATIC
    Code:
      stack=1, locals=1, args_size=1
         0: aload_0
         1: invokevirtual #37                 // Method entity/PolicyPeriod.getProducerCodeOfRecord:()Lentity/ProducerCode;
         4: ifnull        11
         7: iconst_1
         8: goto          12
        11: iconst_0
        12: ireturn
      StackMapTable: number_of_entries = 2
        frame_type = 11 /* same */
        frame_type = 64 /* same_locals_1_stack_item */
          stack = [ int ]
      LineNumberTable:
        line 38: 0
      LocalVariableTable:
        Start  Length  Slot  Name   Signature
            0      13     0 $that$   Lentity/PolicyPeriod;
}
SourceFile: "PolicyPeriodEnhancement.gsx"
  GosuVersion: length = 0xC (unknown attribute)
   31 2E 31 38 2E 37 2D 61 6C 70 68 61
